ovos_ollama_intent_pipeline/__init__.py
ovos_ollama_intent_pipeline/version.py
ovos_ollama_intent_pipeline/locale/ca-es/few_shot_examples.txt
ovos_ollama_intent_pipeline/locale/en-us/few_shot_examples.txt
ovos_ollama_intent_pipeline/locale/mul/few_shot_examples.txt
ovos_ollama_intent_pipeline/locale/mul/prompt_template.txt
ovos_ollama_intent_pipeline/locale/mul/system_prompt.txt
ovos_ollama_intent_pipeline_plugin-0.0.4.dist-info/METADATA
ovos_ollama_intent_pipeline_plugin-0.0.4.dist-info/WHEEL
ovos_ollama_intent_pipeline_plugin-0.0.4.dist-info/entry_points.txt
ovos_ollama_intent_pipeline_plugin-0.0.4.dist-info/top_level.txt
ovos_ollama_intent_pipeline_plugin-0.0.4.dist-info/RECORD
