Metadata-Version: 2.1
Name: ovos-ollama-intent-pipeline-plugin
Version: 0.0.4
Summary: LLM intent engine for OVOS
Home-page: https://github.com/OpenVoiceOS/ovos-ollama-intent-pipeline-plugin
Author: JarbasAI
License: Apache License 2.0
Keywords: natural language processing
Classifier: Development Status :: 5 - Production/Stable
Classifier: Intended Audience :: Developers
Classifier: Topic :: Text Processing :: Linguistic
Classifier: License :: OSI Approved :: Apache Software License
Classifier: Programming Language :: Python :: 3.8
Classifier: Programming Language :: Python :: 3.9
Requires-Dist: ovos-workshop<8.0.0,>=0.1.7
Requires-Dist: ovos-plugin-manager<2.0.0,>=0.5.0
Requires-Dist: ovos-bus-client
Requires-Dist: ovos-config
Requires-Dist: ovos-utils<1.0.0,>=0.3.4
Requires-Dist: requests
Provides-Extra: reranker
Requires-Dist: ovos-flashrank-reranker-plugin; extra == "reranker"
